LICENSE.txt
MANIFEST.in
setup.cfg
setup.py
creaturecast_designer/__init__.py
creaturecast_designer/__main__.py
creaturecast_designer/environment.py
creaturecast_designer/git_hub.py
creaturecast_designer/selection.py
creaturecast_designer.egg-info/PKG-INFO
creaturecast_designer.egg-info/SOURCES.txt
creaturecast_designer.egg-info/dependency_links.txt
creaturecast_designer.egg-info/requires.txt
creaturecast_designer.egg-info/top_level.txt
creaturecast_designer/data/__init__.py
creaturecast_designer/media/__init__.py
creaturecast_designer/media/fonts/__init__.py
creaturecast_designer/media/icons/__init__.py
creaturecast_designer/models/__init__.py
creaturecast_designer/models/abstract_models.py
creaturecast_designer/models/node_library_model.py
creaturecast_designer/models/properties_model.py
creaturecast_designer/models/sidebar_model.py
creaturecast_designer/services/__init__.py
creaturecast_designer/services/download_image.py
creaturecast_designer/services/get_extension.py
creaturecast_designer/services/get_image.py
creaturecast_designer/services/get_stylesheet.py
creaturecast_designer/services/get_user_data.py
creaturecast_designer/services/git.py
creaturecast_designer/services/list_extensions.py
creaturecast_designer/services/pip_functions.py
creaturecast_designer/services/thread_worker.py
creaturecast_designer/services/update_user_data.py
creaturecast_designer/tests/__init__.py
creaturecast_designer/tests/get_user_data.py
creaturecast_designer/tests/run.py
creaturecast_designer/widgets/__init__.py
creaturecast_designer/widgets/avatar_label.py
creaturecast_designer/widgets/connecting_widget.py
creaturecast_designer/widgets/designer_widget.py
creaturecast_designer/widgets/extensions_widget.py
creaturecast_designer/widgets/flow_layout.py
creaturecast_designer/widgets/icon.py
creaturecast_designer/widgets/loading_page.py
creaturecast_designer/widgets/login_widget.py
creaturecast_designer/widgets/pixmap_label.py
creaturecast_designer/widgets/pixmap_push_button.py
creaturecast_designer/widgets/progress_indicator.py
creaturecast_designer/widgets/progress_widget.py
creaturecast_designer/widgets/side_bar.py
creaturecast_designer/widgets/user_header.py
