Metadata-Version: 1.1
Name: creaturecast-designer
Version: 0.0.22
Summary: A gui for downloading launching and managing creaturecast tools
Home-page: https://github.com/Paxtongerrish/creaturecast_designer.git
Author: Paxton Gerrish
Author-email: creaturecastlabs@gmail.com
License: UNKNOWN
Platform: UNKNOWN
Classifier: Development Status :: 3 - Alpha
Classifier: Intended Audience :: End Users/Desktop
Classifier: Topic :: Software Development :: Build Tools
Classifier: License :: OSI Approved :: MIT License
Classifier: Programming Language :: Python :: 2.7
